df_to_sql/__init__.py
df_to_sql/main.py
df_to_sql-2.0.0.dist-info/LICENSE
df_to_sql-2.0.0.dist-info/METADATA
df_to_sql-2.0.0.dist-info/WHEEL
df_to_sql-2.0.0.dist-info/top_level.txt
df_to_sql-2.0.0.dist-info/RECORD
