Metadata-Version: 2.1
Name: df-to-sql
Version: 2.0.0
Author-email: Adam Patterson <adam@faranalytics.net>
Project-URL: Homepage, https://github.com/faranalytics/df_to_sql.git
Project-URL: Bug Tracker, https://github.com/faranalytics/df_to_sql/issues
Classifier: Programming Language :: Python :: 3
Classifier: License :: OSI Approved :: MIT License
Classifier: Operating System :: OS Independent
Requires-Python: >=3.9
License-File: LICENSE
Requires-Dist: alembic (>=1.8.*)
Requires-Dist: pandas (>=1.*)
Requires-Dist: SQLAlchemy (>=1.4.*)
